config/__init__.py
config/config.py
core/__init__.py
core/dictionary.py
core/morphology.py
core/sentiment.py
core/sintaxe.py
core/spellcheck.py
core/statistics.py
core/translation.py
databases/__init__.py
databases/databases.py
databases/tries.py
libraries/__init__.py
libraries/nltkTaggerPortuguese/__init__.py
libraries/nltkTaggerPortuguese/tagger.py
text_ide_Zuap-0.0.1.dist-info/DESCRIPTION.rst
text_ide_Zuap-0.0.1.dist-info/METADATA
text_ide_Zuap-0.0.1.dist-info/RECORD
text_ide_Zuap-0.0.1.dist-info/WHEEL
text_ide_Zuap-0.0.1.dist-info/metadata.json
text_ide_Zuap-0.0.1.dist-info/top_level.txt
tools/__init__.py
