Metadata-Version: 2.0
Name: text-ide-Zuap
Version: 0.0.1
Summary: NLP tools for the TextIDE project
Home-page: https://bitbucket.org/Paulo-Jorge/text-ide-kivy/src/master/
Author: Paulo Martins @ www.paulojorgepm.net
Author-email: paulo.jorge.pm@gmail.com
License: UNKNOWN
Platform: UNKNOWN
Classifier: Programming Language :: Python :: 3
Classifier: License :: OSI Approved :: MIT License
Classifier: Operating System :: OS Independent
Requires-Python: >=3.6
